rwkv_ops/__init__.py
rwkv_ops/mhc_kernel/__init__.py
rwkv_ops/mhc_kernel/native_op.py
rwkv_ops/mhc_kernel/jax_triton_op/mhc_post_op.py
rwkv_ops/mhc_kernel/jax_triton_op/mhc_pre_op.py
rwkv_ops/mhc_kernel/torch_triton_op/mhc_post_op.py
rwkv_ops/mhc_kernel/torch_triton_op/mhc_pre_op.py
rwkv_ops/mhc_kernel/triton_kernel/mhc_post_op.py
rwkv_ops/mhc_kernel/triton_kernel/mhc_pre_op.py
rwkv_ops/rwkv6_kernel/__init__.py
rwkv_ops/rwkv6_kernel/jax_rwkv_kernel.py
rwkv_ops/rwkv6_kernel/ops_rwkv_kernel.py
rwkv_ops/rwkv6_kernel/torch_rwkv_kernel.py
rwkv_ops/rwkv6_kernel/jax_kernel_cuda/gpu_ops.cpp
rwkv_ops/rwkv6_kernel/jax_kernel_cuda/kernel_helpers.h
rwkv_ops/rwkv6_kernel/jax_kernel_cuda/kernels.h
rwkv_ops/rwkv6_kernel/jax_kernel_cuda/pybind11_kernel_helpers.h
rwkv_ops/rwkv6_kernel/jax_kernel_cuda/rwkv_kernels.cu
rwkv_ops/rwkv6_kernel/jax_kernel_hip/gpu_ops.cpp
rwkv_ops/rwkv6_kernel/jax_kernel_hip/kernel_helpers.h
rwkv_ops/rwkv6_kernel/jax_kernel_hip/kernels.h
rwkv_ops/rwkv6_kernel/jax_kernel_hip/pybind11_kernel_helpers.h
rwkv_ops/rwkv6_kernel/jax_kernel_hip/rwkv_kernels.hip
rwkv_ops/rwkv6_kernel/torch_kernel/wkv6_cuda.cu
rwkv_ops/rwkv6_kernel/torch_kernel/wkv6_op.cpp
rwkv_ops/rwkv7_kernel/__init__.py
rwkv_ops/rwkv7_kernel/native_keras_op.py
rwkv_ops/rwkv7_kernel/jax_cuda_kernel/CMakeLists.txt
rwkv_ops/rwkv7_kernel/jax_cuda_kernel/wkv7_ffi.cu
rwkv_ops/rwkv7_kernel/jax_cuda_kernel/wkv7_jax.py
rwkv_ops/rwkv7_kernel/jax_cuda_kernel_single/CMakeLists.txt
rwkv_ops/rwkv7_kernel/jax_cuda_kernel_single/wkv7_single_step_ffi.cu
rwkv_ops/rwkv7_kernel/jax_cuda_kernel_single/wkv7_single_step_jax.py
rwkv_ops/rwkv7_kernel/torch_cuda_kernel/wkv7_cuda.cu
rwkv_ops/rwkv7_kernel/torch_cuda_kernel/wkv7_op.cpp
rwkv_ops/rwkv7_kernel/torch_cuda_kernel/wkv7_torch.py
rwkv_ops/rwkv7_kernel/torch_cuda_kernel_single/wkv7_single_step_cuda.cu
rwkv_ops/rwkv7_kernel/torch_cuda_kernel_single/wkv7_single_step_op.cpp
rwkv_ops/rwkv7_kernel/torch_cuda_kernel_single/wkv7_single_step_torch.py
rwkv_ops-0.7.3.dist-info/METADATA
rwkv_ops-0.7.3.dist-info/WHEEL
rwkv_ops-0.7.3.dist-info/licenses/LICENSE.txt
rwkv_ops-0.7.3.dist-info/RECORD
