Metadata-Version: 2.4
Name: rwkv-ops
Version: 0.7.3
Summary: RWKV operators for multiple backends (PyTorch, JAX, Keras)
Project-URL: Homepage, https://github.com/pass-lin/rwkv_ops
Author-email: pass-lin <qw_lin@qq.com>
License: Apache-2.0
License-File: LICENSE.txt
Classifier: License :: OSI Approved :: Apache Software License
Classifier: Operating System :: OS Independent
Classifier: Programming Language :: Python :: 3
Requires-Python: >=3.8
Requires-Dist: keras>=3.0
